{
	"pages": [ //pages数组中第一项表示应用启动页，参考：https://uniapp.dcloud.io/collocation/pages
		{
			"path": "pages/tabber/index/index",
			"style": {
				"navigationStyle": "custom"
				// "app-plus": {
				// 	"scrollIndicator": "none",
				// 	"titleNView": {
				// 		"backgroundColor": "#FFFFFF",
				// 		"searchInput": {
				// 			"autoFocus": false,
				// 			"align": "center",
				// 			"backgroundColor": "#F7F7F7",
				// 			"borderRadius": "5px",
				// 			"placeholder": "搜索糗事",
				// 			"placeholderColor": "#CCCCCC",
				// 			"disabled": true
				// 		},
				// 		"buttons": [{
				// 				"color": "#FF9619",
				// 				"colorPressed": "#BBBBBB",
				// 				"float": "left",
				// 				"fontSize": "22px",
				// 				"fontSrc": "/static/font/icon.ttf",
				// 				"text": "\ue609"
				// 			},
				// 			// 右边
				// 			{
				// 				"color": "#000000",
				// 				"colorPressed": "#BBBBBB",
				// 				"float": "right",
				// 				"fontSize": "22px",
				// 				"fontSrc": "/static/font/icon.ttf",
				// 				"text": "\ue653"
				// 			}
				// 		]
				// 	}
				// }
			}
		},
		{
			"path": "pages/tabber/dynamic/dynamic",
			"style": {
				"navigationStyle": "custom"
			}
		},
		{
			"path": "pages/demo/demo",
			"style": {
				"navigationBarTitleText": "demo"
			}
		},
		{
			"path": "pages/tabber/chat/chat",
			"style": {
				"navigationStyle": "custom",
				"enablePullDownRefresh": true
			}
		},
		{
			"path": "pages/tabber/home/home",
			"style": {}
		}, {
			"path": "components/index/index-scroll/index-scroll",
			"style": {}
		}, {
			"path": "pages/search/search",
			"style": {
				"enablePullDownRefresh": true,
				"app-plus": {
					"scrollIndicator": "none",
					"titleNView": {
						"autoBackButton": false,
						"backgroundColor": "#FFFFFF",
						"searchInput": {
							"autoFocus": true,
							"align": "left",
							"backgroundColor": "#F7F7F7",
							"borderRadius": "5px",
							"placeholder": "搜索糗事",
							"placeholderColor": "#CCCCCC",
							"disabled": false
						},
						"buttons": [
							// 右边
							{
								"color": "#000000",
								"colorPressed": "#BBBBBB",
								"float": "right",
								"fontSize": "16px",
								"fontSrc": "/static/font/icon.ttf",
								"text": "取消"
							}
						]
					}
				}
			}
		}, {
			"path": "pages/publish/publish",
			"style": {
				"navigationStyle": "custom"
			}
		}, {
			"path": "pages/topic/topic",
			"style": {
				"enablePullDownRefresh": true,
				"app-plus": {
					"scrollIndicator": "none",
					"titleNView": {
						"type": "transparent",
						"buttons": [{
							"type": "menu"
						}]
					}
				},
				"mp-weixin": {
					"scrollIndicator": "none",
					"titleNView": {
						"type": "transparent",
						"buttons": [{
							"type": "menu"
						}]
					}
				}
			}
		}, {
			"path": "pages/follow/follow",
			"style": {
				"navigationStyle": "custom"
			}
		}, {
			"path": "pages/chat-detail/chat-detail",
			"style": {
				"navigationStyle": "custom"
			}
		}
	    ,{
            "path" : "pages/user-info/user-info",
            "style" : {}
        }
    ],
	"globalStyle": {
		"navigationBarTextStyle": "black",
		// "navigationBarTitleText": "仿糗事",
		"navigationBarBackgroundColor": "#FFFFFF",
		"backgroundColor": "#CCCCCC"
	},
	"tabBar": {
		"color": "#CCCCCC",
		"selectedColor": "#FFDF34",
		"borderStyle": "black",
		"backgroundColor": "#FFFFFF",
		"list": [{
			"pagePath": "pages/tabber/index/index",
			"iconPath": "static/tabber/index.png",
			"selectedIconPath": "static/tabber/indexed.png",
			"text": "首页"
		}, {
			"pagePath": "pages/tabber/dynamic/dynamic",
			"iconPath": "static/tabber/dynamic.png",
			"selectedIconPath": "static/tabber/dynamiced.png",
			"text": "动态"
		}, {
			"pagePath": "pages/tabber/chat/chat",
			"iconPath": "static/tabber/chat.png",
			"selectedIconPath": "static/tabber/chated.png",
			"text": "小纸条"
		}, {
			"pagePath": "pages/tabber/home/home",
			"iconPath": "static/tabber/home.png",
			"selectedIconPath": "static/tabber/homeed.png",
			"text": "我的"
		}]
	}
}
